autocbei/Bacillus_subtilis.part500.cds.all.fa
autocbei/__init__.py
autocbei/cbei/__init__.py
autocbei/cbei/autoCBEI.py
autocbei/cbei/cbei.py
autocbei/cbei/judges.py
autocbei/cbei/stat.py
autocbei-1.8.dist-info/LICENSE
autocbei-1.8.dist-info/METADATA
autocbei-1.8.dist-info/WHEEL
autocbei-1.8.dist-info/entry_points.txt
autocbei-1.8.dist-info/top_level.txt
autocbei-1.8.dist-info/RECORD
